container/Dockerfile
container/__init__.py
container/common.py
container/readme.md
container/requirements.txt
container/write.py
dora_aws/__init__.py
dora_aws/job/readme.md
dora_aws/job/templates/read.py.jinja
dora_aws/job/templates/write.py.jinja
dora_aws/plugins/__init__.py
dora_aws/plugins/engines/__init__.py
dora_aws/plugins/engines/function.py
dora_aws/plugins/sensors/__init__.py
dora_aws/plugins/sensors/rule.py
dora_aws/plugins/sensors/sqs.py
dora_aws/plugins/volumes/__init__.py
dora_aws/plugins/volumes/s3.py
dora_aws/utils.py
dora_aws-0.1.0.dist-info/LICENSE
dora_aws-0.1.0.dist-info/METADATA
dora_aws-0.1.0.dist-info/WHEEL
dora_aws-0.1.0.dist-info/RECORD
